src/__init__.py
src/mhaptk2.py
mHapTk2-1.1.dist-info/LICENSE.txt
mHapTk2-1.1.dist-info/METADATA
mHapTk2-1.1.dist-info/WHEEL
mHapTk2-1.1.dist-info/entry_points.txt
mHapTk2-1.1.dist-info/top_level.txt
mHapTk2-1.1.dist-info/RECORD
